dsapi_llmclient-0.1.5.dist-info/licenses/LICENSE
llmclient/__init__.py
llmclient/cache.py
llmclient/client.py
llmclient/config.py
llmclient/logger.py
llmclient/utils.py
tests/__init__.py
tests/test_basic.py
dsapi_llmclient-0.1.5.dist-info/METADATA
dsapi_llmclient-0.1.5.dist-info/WHEEL
dsapi_llmclient-0.1.5.dist-info/top_level.txt
dsapi_llmclient-0.1.5.dist-info/RECORD
