Metadata-Version: 2.4
Name: dsapi-llmclient
Version: 0.1.5
Summary: 轻量级LLM API客户端库，支持缓存、重试和详细日志记录功能
Home-page: https://github.com/leo/dsapi
Author: Leo
Author-email: marticle.ios@gmail.com
Classifier: Programming Language :: Python :: 3
Classifier: License :: OSI Approved :: MIT License
Classifier: Operating System :: OS Independent
Requires-Python: >=3.6
License-File: LICENSE
Requires-Dist: requests>=2.25.0
Requires-Dist: tenacity>=8.0.0
Requires-Dist: python-dotenv>=0.19.0
Requires-Dist: jsonschema>=4.0.0
Dynamic: author
Dynamic: author-email
Dynamic: classifier
Dynamic: description
Dynamic: description-content-type
Dynamic: home-page
Dynamic: license-file
Dynamic: requires-dist
Dynamic: requires-python
Dynamic: summary
